torchexpo/__init__.py
torchexpo/version.py
torchexpo/model/__init__.py
torchexpo/model/base_model.py
torchexpo/model/model.py
torchexpo/model/utils.py
torchexpo/tasks/__init__.py
torchexpo/tasks/base_task.py
torchexpo/tasks/tasks.py
torchexpo/tasks/audio/__init__.py
torchexpo/tasks/nlp/__init__.py
torchexpo/tasks/vision/__init__.py
torchexpo/tasks/vision/image_classification.py
torchexpo/tasks/vision/object_detection.py
torchexpo/tasks/vision/semantic_segmentation.py
torchexpo-2.0.0a1.dist-info/LICENSE
torchexpo-2.0.0a1.dist-info/METADATA
torchexpo-2.0.0a1.dist-info/WHEEL
torchexpo-2.0.0a1.dist-info/top_level.txt
torchexpo-2.0.0a1.dist-info/zip-safe
torchexpo-2.0.0a1.dist-info/RECORD
