Metadata-Version: 2.1
Name: torchexpo
Version: 2.0.0a1
Summary: Collection of models and extensions for deployment in PyTorch
Home-page: https://github.com/torchexpo/torchexpo
Download-URL: https://github.com/torchexpo/torchexpo/tags
Author: Omkar Prabhu
Author-email: Omkar Prabhu <prabhuomkar@pm.me>
License: Apache-2.0
Project-URL: Homepage, https://github.com/torchexpo/torchexpo
Project-URL: Bug Tracker, https://github.com/torchexpo/torchexpo/issues
Classifier: Development Status :: 3 - Alpha
Classifier: Intended Audience :: Developers
Classifier: Intended Audience :: Education
Classifier: Intended Audience :: Science/Research
Classifier: License :: OSI Approved :: Apache Software License
Classifier: Topic :: Scientific/Engineering
Classifier: Topic :: Scientific/Engineering :: Mathematics
Classifier: Topic :: Scientific/Engineering :: Artificial Intelligence
Classifier: Topic :: Software Development
Classifier: Topic :: Software Development :: Libraries
Classifier: Topic :: Software Development :: Libraries :: Python Modules
Classifier: Programming Language :: Python :: 3
Requires-Python: >=3.7
License-File: LICENSE
Requires-Dist: torch
Requires-Dist: torchvision
